funhtml/__init__.py
funhtml/pd2html.py
funhtml/pyhtml.py
funhtml-1.0.3.dist-info/METADATA
funhtml-1.0.3.dist-info/WHEEL
funhtml-1.0.3.dist-info/top_level.txt
funhtml-1.0.3.dist-info/RECORD
