Metadata-Version: 2.4
Name: funhtml
Version: 1.0.3
Summary: funhtml
Author-email: 牛哥 <niuliangtao@qq.com>, farfarfun <farfarfun@qq.com>
Maintainer-email: 牛哥 <niuliangtao@qq.com>, farfarfun <farfarfun@qq.com>
Project-URL: Organization, https://github.com/farfarfun
Project-URL: Repository, https://github.com/farfarfun/funhtml
Project-URL: Releases, https://github.com/farfarfun/funhtml/releases
Requires-Python: >=3.8
